core_evals/genai_perf/__init__.py
core_evals/genai_perf/framework.yml
core_evals/genai_perf/framework_entrypoint.py
core_evals/genai_perf/output.py
genai_perf_eval/__init__.py
genai_perf_eval/main.py
nvidia_genai_perf_eval-25.11.dist-info/licenses/LICENSE
nvidia_genai_perf_eval-25.11.dist-info/METADATA
nvidia_genai_perf_eval-25.11.dist-info/WHEEL
nvidia_genai_perf_eval-25.11.dist-info/entry_points.txt
nvidia_genai_perf_eval-25.11.dist-info/top_level.txt
nvidia_genai_perf_eval-25.11.dist-info/RECORD
