Metadata-Version: 2.4
Name: nvidia_genai_perf_eval
Version: 25.11
Summary: GenAI Perf - packaged by NVIDIA Evals Factory
License:                                  Apache License
Project-URL: Homepage, https://github.com/triton-inference-server/server
Project-URL: Bug Tracker, https://github.com/triton-inference-server/server/issues
Classifier: Development Status :: 5 - Production/Stable
Classifier: Programming Language :: Python :: 3
Classifier: License :: OSI Approved :: Apache Software License
Classifier: Operating System :: OS Independent
Requires-Python: >=3.10
License-File: LICENSE
Requires-Dist: genai-perf==0.0.9
Requires-Dist: nemo-evaluator
Dynamic: license-file
